odoo10_addon_sale_order_import_csv-10.0.1.0.0.99.dev3-py2.7-nspkg.pth
odoo/addons/sale_order_import_csv/README.rst
odoo/addons/sale_order_import_csv/__init__.py
odoo/addons/sale_order_import_csv/__manifest__.py
odoo/addons/sale_order_import_csv/i18n/sale_order_import_csv.pot
odoo/addons/sale_order_import_csv/static/description/icon.png
odoo/addons/sale_order_import_csv/tests/__init__.py
odoo/addons/sale_order_import_csv/tests/test_csv_order_import.py
odoo/addons/sale_order_import_csv/tests/files/order_file_test1.csv
odoo/addons/sale_order_import_csv/tests/files/order_file_test1_update.csv
odoo/addons/sale_order_import_csv/wizard/__init__.py
odoo/addons/sale_order_import_csv/wizard/sale_order_import.py
odoo10_addon_sale_order_import_csv-10.0.1.0.0.99.dev3.dist-info/METADATA
odoo10_addon_sale_order_import_csv-10.0.1.0.0.99.dev3.dist-info/RECORD
odoo10_addon_sale_order_import_csv-10.0.1.0.0.99.dev3.dist-info/WHEEL
odoo10_addon_sale_order_import_csv-10.0.1.0.0.99.dev3.dist-info/namespace_packages.txt
odoo10_addon_sale_order_import_csv-10.0.1.0.0.99.dev3.dist-info/top_level.txt
